LICENSE
MANIFEST.in
README.md
requirements.txt
setup.py
tuya_bulb_control/__init__.py
tuya_bulb_control/_tuya_api.py
tuya_bulb_control/bulb.py
tuya_bulb_control/exceptions.py
tuya_bulb_control/project.ini
tuya_bulb_control.egg-info/PKG-INFO
tuya_bulb_control.egg-info/SOURCES.txt
tuya_bulb_control.egg-info/dependency_links.txt
tuya_bulb_control.egg-info/not-zip-safe
tuya_bulb_control.egg-info/requires.txt
tuya_bulb_control.egg-info/top_level.txt