Metadata-Version: 2.1
Name: tuya-bulb-control
Version: 0.1b3
Summary: Tuya Bulb Control - API wrapper for you smart bulbs developed by Tuya
Home-page: https://github.com/Octoober/tuya-bulb-control
Author: Kirill Hickey
License: MIT
Keywords: iot tuya api wrapper
Platform: UNKNOWN
Classifier: Development Status :: 4 - Beta
Classifier: Intended Audience :: Developers
Classifier: License :: OSI Approved :: MIT License
Classifier: Programming Language :: Python
Classifier: Programming Language :: Python :: 3
Classifier: Programming Language :: Python :: 3.6
Classifier: Programming Language :: Python :: 3.7
Classifier: Programming Language :: Python :: 3.8
